pytest_custom_report.py
pytest_custom_report-1.0.1.dist-info/LICENSE
pytest_custom_report-1.0.1.dist-info/METADATA
pytest_custom_report-1.0.1.dist-info/WHEEL
pytest_custom_report-1.0.1.dist-info/entry_points.txt
pytest_custom_report-1.0.1.dist-info/top_level.txt
pytest_custom_report-1.0.1.dist-info/RECORD
