Metadata-Version: 2.1
Name: pytest-custom-report
Version: 1.0.1
Summary: Configure the symbols displayed for test outcomes
Home-page: https://github.com/wimglenn/pytest-custom-report
Author: Wim Glenn
Author-email: hey@wimglenn.com
License: MIT
Platform: UNKNOWN
Classifier: Framework :: Pytest
Classifier: Programming Language :: Python
Classifier: Programming Language :: Python :: 2
Classifier: Programming Language :: Python :: 3
Requires-Dist: pytest
